maat_machine/__init__.py
maat_machine/archive.py
maat_machine/data_images.py
maat_machine/directory_tree.py
maat_machine/filesystem.py
maat_machine/logging.py
maat_machine/model/__init__.py
maat_machine/model/cv.py
maat_machine/model/utils.py
maat_machine/packages.py
maat_machine/plots.py
maat_machine/pprint.py
maat_machine/time.py
maat_machine/utils.py
maat_machine-0.1.0.dist-info/LICENSE
maat_machine-0.1.0.dist-info/WHEEL
maat_machine-0.1.0.dist-info/METADATA
maat_machine-0.1.0.dist-info/RECORD
