Metadata-Version: 2.1
Name: maat-machine
Version: 0.1.0
Summary: Yet another package designed to simplify coding for data science and machine learning
License: MIT
Author: Dmitry Vlasov
Author-email: dmitry.v.vlasov@gmail.com
Requires-Python: ==3.11.9
Classifier: License :: OSI Approved :: MIT License
Classifier: Programming Language :: Python :: 3
Requires-Dist: ipython (>=8.24.0,<9.0.0)
Requires-Dist: matplotlib (>=3.8.4,<4.0.0)
Requires-Dist: numpy (==1.26.4)
Requires-Dist: opencv-python (>=4.9.0.80,<5.0.0.0)
Requires-Dist: pandas (>=2.2.2,<3.0.0)
Requires-Dist: pillow (>=10.3.0,<11.0.0)
Requires-Dist: scikit-learn (>=1.4.2,<2.0.0)
Requires-Dist: tensorflow (==2.16.1)
Requires-Dist: tqdm (>=4.66.4,<5.0.0)
